enc_dec/encoder_decoder.py
Ani_Encrypt-2.0.1.dist-info/LICENSE
Ani_Encrypt-2.0.1.dist-info/METADATA
Ani_Encrypt-2.0.1.dist-info/WHEEL
Ani_Encrypt-2.0.1.dist-info/entry_points.txt
Ani_Encrypt-2.0.1.dist-info/top_level.txt
Ani_Encrypt-2.0.1.dist-info/RECORD
