Metadata-Version: 2.1
Name: Ani-Encrypt
Version: 2.0.1
Summary: A Python package to encrypt and decrypt data.
Home-page: UNKNOWN
Author: Aniket Dubey
Author-email: daniket182@gmail.com
License: MIT
Platform: UNKNOWN
Classifier: License :: OSI Approved :: MIT License
Classifier: Programming Language :: Python :: 3
Classifier: Programming Language :: Python :: 3.7
Requires-Dist: requests
